[{"key": "M-:", "id": "b89591aa-09a7-4f37-9a94-6b9d9710fe08", "context": "emacs", "note": "\r\n\t\t  \r\n\t\t    No notes.\r\n\t\t  \r\n\t\t", "tags": null, "name": "eval-minibuffer", "description": "Pops into a minibuffer for evaluating expressions.&nbsp; Useful for navigating emacs' twisty elisp stuffs."}, {"key": "C-h b", "id": "878371dc-543b-4df5-a978-7c739bc24298", "context": "emacs", "note": null, "tags": null, "name": "descbinds", "description": "list all bindings"}, {"key": "C-x k", "id": "55cd0896-abea-4c83-92ec-7c2db52cd405", "context": "emacs", "note": "\r\n\t\t  Note\r\n\t\t", "tags": null, "name": "kill-buffer", "description": "Kill buffer by name.&nbsp; Prompts for input."}, {"key": "M-k", "id": "8cb192b6-4917-42be-aa2e-3d19509a6df3", "context": "emacs", "note": "\r\n\t\t  Note\r\n\t\t", "tags": null, "name": "kill-sentence", "description": "Kill from point to end of sentence."}, {"key": "M-r REGX &lt;RET&gt;", "id": "f8953633-089e-4559-9f0e-443cdb8fa074", "context": "emacs", "note": "\r\n\t\t  Note\r\n\t\t", "tags": null, "name": "regexp for minibuffer history", "description": "Regex search through previous minibuffer history"}, {"key": "*", "id": "3b93655b-dfc0-4084-8d8b-bd27704187f0", "context": "vim", "note": "\r\n\t\t  Note\r\n\t\t", "tags": null, "name": "goto next", "description": "Find the next example of word under cursor."}, {"key": "-config-", "id": "68c738bd-9946-4c3d-be66-7c82a4bd7140", "context": "vim", "note": "\r\n\t\t  \r\n\t\t    \r\n\t\t  Note\r\n\t\t\r\n\t\t  \r\n\t\t", "tags": null, "name": "incsearch", "description": "If you set the incsearch option, Vim will show the first match for the pattern, while you are still typing it"}, {"key": "%", "id": "e3ef1d52-4ca2-4f73-8d00-20b4219be8b9", "context": "vim", "note": "\r\n\t\t  \r\n\t\t    \r\n\t\t  Note\r\n\t\t\r\n\t\t  \r\n\t\t", "tags": null, "name": "jump-to-brace", "description": "Jump to matching closing brace."}, {"key": "\\[&nbsp;", "id": "a42063ae-0574-4170-8266-f0b56906cf6f", "context": "vim", "note": "\r\n\t\t  Note\r\n\t\t", "tags": null, "name": "adv. move", "description": "Each triggers a command to go forwards `]` or backwards `[` by things like closing parens and marks."}, {"key": "C-[ / ]", "id": "4f88ccff-477c-4937-91f4-0e447bcdf4c1", "context": "vim", "note": "\r\n\t\t  Note\r\n\t\t", "tags": null, "name": "jump-block", "description": "Move &gt; or &lt;, by block."}, {"key": ".", "id": "9704fac2-d051-475a-9e74-3310652b13db", "context": "vim", "note": "\r\n\t\t  Note\r\n\t\t", "tags": null, "name": "repeat-last-change", "description": "Repeat last command (like change-word)"}, {"key": "q &lt;register&gt;", "id": "f94a21d3-d4f8-49f1-bc1f-ca4c5213ebc4", "context": "vim", "note": "\r\n\t\t  Note\r\n\t\t", "tags": null, "name": "record-macro", "description": "Start recording into &lt;register&gt;"}, {"key": "@ &lt;register&gt;", "id": "48afbce6-2d2f-4720-966f-04013075dc67", "context": "vim", "note": "\r\n\t\t  Note\r\n\t\t", "tags": null, "name": "play-macro", "description": "Playback macro at &lt;register&gt;"}, {"key": ":grep", "id": "dd106cf5-e702-45d7-a11c-72e99b1affb5", "context": "vim", "note": "\r\n\t\t  Note\r\n\t\t", "tags": null, "name": "grep-files", "description": "description goes here"}, {"key": "C-M-\\", "id": "3ff2f4d0-4243-4272-977d-2356fcd1cfe4", "context": "emacs", "note": "\r\n\t\t  Note\r\n\t\t", "tags": null, "name": "indent-region", "description": "Indent the region"}]